figmex_mcp_bridge/__init__.py
figmex_mcp_bridge/__main__.py
figmex_mcp_bridge/bridge.py
figmex_mcp_bridge/cli.py
figmex_mcp_bridge/server.py
figmex_mcp_bridge-0.2.1.dist-info/licenses/LICENSE
figmex_mcp_bridge-0.2.1.dist-info/METADATA
figmex_mcp_bridge-0.2.1.dist-info/WHEEL
figmex_mcp_bridge-0.2.1.dist-info/entry_points.txt
figmex_mcp_bridge-0.2.1.dist-info/top_level.txt
figmex_mcp_bridge-0.2.1.dist-info/RECORD
