Metadata-Version: 2.4
Name: figmex-mcp-bridge
Version: 0.2.1
Summary: MCP bridge that connects Codex CLI to the Figmex Figma plugin over WebSocket.
Author: Austin Wells
License-Expression: MIT
Project-URL: homepage, https://github.com/austinwells/Figmex-MCP-Bridge
Project-URL: issues, https://github.com/austinwells/Figmex-MCP-Bridge/issues
Classifier: Programming Language :: Python :: 3
Classifier: Programming Language :: Python :: 3.10
Classifier: Programming Language :: Python :: 3.11
Classifier: Programming Language :: Python :: 3.12
Classifier: Operating System :: OS Independent
Requires-Python: >=3.10
License-File: LICENSE
Requires-Dist: fastmcp>=2.8.0
Requires-Dist: websockets>=12.0
Requires-Dist: pydantic>=2.6
Requires-Dist: python-dotenv>=1.0
Provides-Extra: dev
Requires-Dist: pytest>=7.0; extra == "dev"
Requires-Dist: ruff>=0.4; extra == "dev"
Dynamic: license-file
